clock.v
/* clock */
`timescale 1s/1ms
module clock(output clk);
    reg theClock = 1;
    reg [15:0] counter = 0;

    assign clk = theClock;
    
    always begin
        #5000;
        theClock = !theClock;
        counter = counter + 1;
        if(counter > 1000) begin
        	//$finish;
        end

    end
endmodule

engine.v
`timescale 1ms/1ms    

/*

ID Legend:
- 0: ?

*/

`define UNKNOWN 0
`define CURRENT 1
`define ENTRANCE 2
`define EXIT 3
`define BLANK 4
`define WALL 5
`define ENEMY 6

module main();
	initial begin

		//$dumpfile("cpu.vcd");
		$readmemh("input.data",input_data);
		$readmemh("map.data", map_data);
		//$dumpvars(1,main);

		//initialize bitmap to 0
		for(i = 0; i < 20; i = i + 1) begin
			for(j = 0; j < 20; j = j + 1) begin
				bitmap[i*20 + j] = 0;
			end
		end

	/* Copy pasta necessary because verilog 2001 doesn't support > 2D arrays.
	   Used to load map data from user */
		for(i = 0; i < 20; i = i+1) begin
			map[i*20 + 0] = map_data[i][79:76];
			map[i*20 + 1] = map_data[i][75:72];
			map[i*20 + 2] = map_data[i][71:68];
			map[i*20 + 3] = map_data[i][67:64];
			map[i*20 + 4] = map_data[i][63:60];
			map[i*20 + 5] = map_data[i][59:56];
			map[i*20 + 6] = map_data[i][55:52];
			map[i*20 + 7] = map_data[i][51:48];
			map[i*20 + 8] = map_data[i][47:44];
			map[i*20 + 9] = map_data[i][43:40];
			map[i*20 + 10] = map_data[i][39:36];
			map[i*20 + 11] = map_data[i][35:32];
			map[i*20 + 12] = map_data[i][31:28];
			map[i*20 + 13] = map_data[i][27:24];
			map[i*20 + 14] = map_data[i][23:20];
			map[i*20 + 15] = map_data[i][19:16];
			map[i*20 + 16] = map_data[i][15:12];
			map[i*20 + 17] = map_data[i][11:8];
			map[i*20 + 18] = map_data[i][7:4];
			map[i*20 + 19] = map_data[i][3:0];
		end
	end

	wire[3:0] current_val = map_data[0][79:76];
	wire[3:0] current_val2 = map_data[1][75:72];

	integer f, number;
	reg[15:0]i; //multi-purpose indices
	reg[15:0]j;
	reg[15:0]eip = 0; //command pointer
	wire clk;
	clock c0(clk);

	reg[2:0] current_random = 0;
	reg[2:0] run_random = 0;

	reg [15:0]input_data[0:2000]; //Array of all command data
	reg [79:0]map_data[0:19]; //used to load up the map

	reg [15:0]map[1000:0]; //pseudo 10x10 2D array of 16 bit values
	reg bitmap[1000:0]; //Literally a bitmap haha
	reg display_queued = 1;

	reg [15:0]current_pos = 50;
	wire[15:0] current_command = input_data[eip];

	wire new_command = !(^input_data[eip] === 1'bx);

	wire left_clear = (current_pos - 1 > 0 && (current_pos - 1) % 20 < current_pos % 20);
	wire left_2_clear = (current_pos - 2 > 0 && (current_pos - 2) % 20 < current_pos % 20);
	wire right_clear = (current_pos + 1 < 400 && (current_pos + 1) % 20 > current_pos % 20);
	wire right_2_clear = (current_pos + 2 < 400 && (current_pos + 2) % 20 > current_pos % 20);
	wire top_clear = (current_pos - 20 > 0);
	wire top_2_clear = (current_pos - 40 > 0);
	wire bottom_clear = (current_pos + 20 < 400);
	wire bottom_2_clear = (current_pos + 40 < 400);

	reg can_move = 1;
	reg can_fight = 0;
	reg can_hacks = 1;

	/* Player information */
	reg [15:0]player_health = 100;
	reg [15:0]player_max_health = 100;
	wire [15:0]player_health_ratio = (player_health * 10 / player_max_health);

	/* Game data */
	wire on_enemy = map[current_pos] == `ENEMY;
	reg run_failed = 0;

	/* Settings */
	reg no_clip = 0;
	reg no_shroud = 0;
	reg godmode = 0;

	always @(posedge clk) begin
			
       
		current_random <= $random % 4;
		run_random <= $random % 3;
		//end

		if(top_clear) begin
			bitmap[current_pos - 20] <= 1;
			if(left_clear)
				bitmap[current_pos - 20 - 1] <= 1;
			if(right_clear)
				bitmap[current_pos - 20 + 1] <= 1;
		end
		if(top_2_clear)
			bitmap[current_pos - 40] <= 1;			
		if(bottom_clear) begin
			bitmap[current_pos + 20] <= 1;
			if(left_clear)
				bitmap[current_pos + 20 - 1] <= 1;
			if(right_clear)
				bitmap[current_pos + 20 + 1] <= 1;			
		end
		if(bottom_2_clear)
			bitmap[current_pos + 40] <= 1;
		if(right_clear)
			bitmap[current_pos + 1] <= 1;
		if(right_2_clear)
			bitmap[current_pos + 2] <= 1;			
		if(left_clear)
			bitmap[current_pos - 1] <= 1;
		if(left_2_clear)
			bitmap[current_pos - 2] <= 1;

		if(new_command) begin //prints out current information
			display_queued <= 1;
			case(input_data[eip])
				1: begin
					if (current_pos + 1 > 0 && (current_pos + 1) % 20 > current_pos % 20)
						if(map[current_pos + 1] != 5)
							current_pos <= current_pos + 1;
				end
				2: begin //le
					if (current_pos - 1 > 0 && (current_pos - 1) % 20 < current_pos % 20)
						if(map[current_pos - 1] != 5)
							current_pos <= current_pos - 1;
				end
				3: begin //up
					if(current_pos - 20 > 0)
						if(map[current_pos - 20] != 5)
							current_pos <= current_pos - 20;
				end
				4: begin //down
					if(current_pos + 20 < 400)
						if(map[current_pos + 20] != 5)
							current_pos <= current_pos + 20;
				end
				5: begin //attack
					player_health <= player_health - 10;
				end	
				6: begin //run
					if(run_random > 0) begin
						case(current_random)
						0: begin //right
							if (current_pos + 1 > 0 && (current_pos + 1) % 20 > current_pos % 20)
								if(map[current_pos + 1] != 5)
									current_pos <= current_pos + 1;
						end
						1: begin //left
							if (current_pos - 1 > 0 && (current_pos - 1) % 20 < current_pos % 20)
								if(map[current_pos - 1] != 5)
									current_pos <= current_pos - 1;
						end
						2: begin //up
							if(current_pos - 20 > 0 & map[current_pos - 20] != 5)
								current_pos <= current_pos - 20;
						end
						3: begin //down
							if(current_pos + 20 < 400 & map[current_pos + 20] != 5)
								current_pos <= current_pos + 20;
						end
						endcase
					end
					else begin
						run_failed <= 1;
					end

				end												
				16'h10: begin //exit
					no_shroud <= !no_shroud;
					$display("No shroud");
				end
				11: begin // no_shroud
					
				end											
			endcase
			eip <= eip + 1;
		end
		else begin
			$readmemh("input.data",input_data);
		end
		if(display_queued) begin

			$display("wiejfoweifjweif");

			if(!new_command)
				display_queued <= 0; 
			f = $fopen("output.data");
			
			if(run_failed) begin
				$fdisplay(f, "RUN FAILED");
				run_failed <= 0;
			end

			for(i = 0; i < 20; i = i + 1) begin
				for(j = 0; j < 20; j = j + 1) begin
					$fwrite(f, "%d ", bitmap[i*20 + j]);
				end
				$fdisplay(f, "");
			end
			$fdisplay(f, "current pos: %d", current_pos);
			$fdisplay(f, $time, "is current time.");

			if(on_enemy) begin //draw enemy if reached enemy
				 $fdisplay(f, "\n~~~~~~~~~~~~~~~~~~~~~~~~~~~~~~~~~~~~~~~~~~~~~~~~~~~~~~~~~~~~~~~~~~~~~~~~~~~~~~~~~~~");
				 $fdisplay(f, "               EVENT: You have encountered an enemy!");
				 $fdisplay(f, "~~~~~~~~~~~~~~~~~~~~~~~~~~~~~~~~~~~~~~~~~~~~~~~~~~~~~~~~~~~~~~~~~~~~~~~~~~~~~~~~~~~\n");
				 $fdisplay(f,"                   ,===:'.,            `-._ \n                    `:.`---.__         `-._   \n                      `:.     `--.         `.   \n                        \\.        `.         `.   \n                (,,(,    \\.         `.   ____,-`.,  \n             (,'     `/   \\.   ,--.___`.'   \n         ,  ,'  ,--.  `,   \\.;'         `   \n          `{D, {    \\  :    \\;   \n            V,,'    /  /    //   \n            j;;    /  ,' ,-//.    ,---.      ,  \n            \\;'   /  ,' /  _  \\  /  _  \\   ,'/  \n                  \\   `'  / \\  `'  / \\  `.' /   \n                   `.___,'   `.__,'   `.__,'  	\n"         );
			end
			else begin
				 $fdisplay(f, "\n~~~~~~~~~~~~~~~~~~~~~~~~~~~~~~~~~~~~~~~~~~~~~~~~~~~~~~~~~~~~~~~~~~~~~~~~~~~~~~~~~~~");
				 $fdisplay(f, "               MAP: Dungeon of Illore");
				 $fdisplay(f, "~~~~~~~~~~~~~~~~~~~~~~~~~~~~~~~~~~~~~~~~~~~~~~~~~~~~~~~~~~~~~~~~~~~~~~~~~~~~~~~~~~~\n");
				for(i = 0; i < 20; i = i + 1) begin
					$fwrite(f, "");
					for(j = 0; j < 20; j = j + 1) begin
						if(current_pos == i*20 + j) begin
							$fwrite(f, "! " );
						end
						else if(bitmap[i*20 + j] == 0 && no_shroud == 0) begin
							$fwrite(f, "? " );
						end
						else begin
							case(map[i*20 + j])
								`CURRENT: begin
									$fwrite(f, "! ");
								end
								`ENTRANCE: begin
									$fwrite(f, "< ");
								end
								`EXIT: begin
									$fwrite(f, "> ");
								end		
								`BLANK: begin
									$fwrite(f, "  ");
								end
								`WALL: begin
									$fwrite(f, "X ");
								end	
								`ENEMY: begin
									$fwrite(f, "@ ");
								end																			
							endcase							
						end
					end
					$fdisplay(f, "");
				end
			end
			$fwrite(f, "\nHP: [%d/%d]\n", player_health, player_max_health);
			$fwrite(f, "\nNO_SHROUD: [%d]\n", no_shroud);




			if(on_enemy) begin
				$fwrite(f, "\nEnemy HP: [%d/%d]", player_health, player_max_health);
			end
			/* Writing allowed commands */
			$fdisplay(f, "\n");
			if(can_move & !on_enemy)
				$fwrite(f, "[1] - Right    [2] - Left    [3] - Up    [4] - Down    ");
			if(on_enemy)
				$fwrite(f, "[5] - Attack    [6] - Run    ");
			if(can_hacks)
				$fwrite(f, "[10] - No shroud    ");

			$fdisplay(f, "\n");
			$fclose(f);
		end
	end


endmodule

dump.vcd
$date
	Wed Dec  2 04:12:25 2015
$end
$version
	Icarus Verilog
$end
$timescale
	1ms
$end
$scope module main $end
$var wire 1 ! bottom_2_clear $end
$var wire 1 " bottom_clear $end
$var wire 1 # clk $end
$var wire 16 $ current_command [15:0] $end
$var wire 4 % current_val [3:0] $end
$var wire 4 & current_val2 [3:0] $end
$var wire 1 ' left_2_clear $end
$var wire 1 ( left_clear $end
$var wire 1 ) new_command $end
$var wire 1 * on_enemy $end
$var wire 16 + player_health_ratio [15:0] $end
$var wire 1 , right_2_clear $end
$var wire 1 - right_clear $end
$var wire 1 . top_2_clear $end
$var wire 1 / top_clear $end
$var reg 1 0 can_fight $end
$var reg 1 1 can_hacks $end
$var reg 1 2 can_move $end
$var reg 16 3 current_pos [15:0] $end
$var reg 3 4 current_random [2:0] $end
$var reg 1 5 display_queued $end
$var reg 16 6 eip [15:0] $end
$var integer 32 7 f [31:0] $end
$var reg 1 8 godmode $end
$var reg 16 9 i [15:0] $end
$var reg 16 : j [15:0] $end
$var reg 1 ; no_clip $end
$var reg 1 < no_shroud $end
$var reg 16 = player_health [15:0] $end
$var reg 16 > player_max_health [15:0] $end
$var reg 1 ? run_failed $end
$var reg 3 @ run_random [2:0] $end
$upscope $end
$enddefinitions $end
#0
$dumpvars
b0 @
0?
b1100100 >
b1100100 =
0<
0;
b10100 :
b10100 9
08
bx 7
b0 6
15
b0 4
b110010 3
12
11
00
1/
1.
1-
1,
b1010 +
0*
1)
1(
1'
b100 &
b101 %
b0 $
1#
1"
1!
$end
#500000
0#
#1000000
b1 6
b1 $
b111 @
b10100 :
b10100 9
b10 7
1#
#1500000
0#
#2000000
b10 6
b10 $
b110011 3
b110 @
b101 4
b10100 :
b10100 9
1#
#2500000
0#
#3000000
b11 6
b11 $
b110010 3
b10 @
b1 4
b10100 :
b10100 9
1#
#3500000
0#
#4000000
b100 6
b100 $
b0 @
b101 4
b10100 :
b10100 9
1#
#4500000
0#
#5000000
b101 6
bx $
0)
b1 @
b1 4
b10100 :
b10100 9
1#
#5500000
0#
#6000000
05
b10 @
b10 4
b10100 :
b10100 9
1#
#6500000
0#
#7000000
b1 @
b1 4
1#
#7500000
0#
#8000000
b111 @
1#
#8500000
0#
#9000000
b101 4
1#
#9500000
0#
#10000000
b1 4
1#
#10500000
0#
#11000000
b0 @
b110 4
1#
#11500000
0#
#12000000
b111 @
b10 4
1#
#12500000
0#
#13000000
b0 @
b0 4
1#
#13500000
0#
#14000000
b110 @
1#
#14500000
0#
#15000000
b0 @
b101 4
1#
#15500000
0#
#16000000
b1 @
b111 4
1#
#16500000
0#
#17000000
b0 4
1#
#17500000
0#
#18000000
b111 @
b10 4
1#
#18500000
0#
#19000000
b110 4
1#
#19500000
0#
#20000000
b101 4
1#
#20500000
0#
#21000000
b0 @
b11 4
1#
#21500000
0#
#22000000
b111 @
b110 4
1#
#22500000
0#
#23000000
b110 @
b1 4
1#
#23500000
0#
#24000000
b10 @
b11 4
1#
#24500000
0#
#25000000
b0 @
b110 4
1#
#25500000
0#
#26000000
b10 @
b10 4
1#
#26500000
0#
#27000000
b111 @
b1 4
1#
#27500000
0#
#28000000
b0 4
1#
#28500000
0#
#29000000
b1 @
b11 4
1#
#29500000
0#
#30000000
b10 4
1#
#30500000
0#
#31000000
b10 @
b0 4
1#
#31500000
0#
#32000000
b110 @
b111 4
1#
#32500000
0#
#33000000
b1 @
b1 4
1#
#33500000
0#
#34000000
b0 @
b111 4
1#
#34500000
0#
#35000000
b110 4
1#
#35500000
0#
#36000000
b1 @
b1 4
1#
#36500000
0#
#37000000
b10 4
1#
#37500000
0#
#38000000
b10 @
b11 4
1#
#38500000
0#
#39000000
b0 @
b0 4
1#
#39500000
0#
#40000000
b110 @
b111 4
1#
#40500000
0#
#41000000
b10 @
1#
#41500000
0#
#42000000
b111 @
b101 4
1#
#42500000
0#
#43000000
b0 @
b111 4
1#
#43500000
0#
#44000000
b10 4
1#
#44500000
0#
#45000000
b110 4
1#
#45500000
0#
#46000000
b111 4
1#
#46500000
0#
#47000000
b10 4
1#
#47500000
0#
#48000000
b10 @
b1 4
1#
#48500000
0#
#49000000
b0 @
b11 4
1#
#49500000
0#
#50000000
b110 @
b1 4
1#
#50500000
0#
#51000000
b10 @
b11 4
1#
#51500000
0#
#52000000
b1 @
b111 4
1#
#52500000
0#
#53000000
b0 @
b0 4
1#
#53500000
0#
#54000000
b111 @
b110 4
1#
#54500000
0#
#55000000
b10 4
1#
#55500000
0#
#56000000
b0 @
b11 4
1#
#56500000
0#
#57000000
b110 @
b111 4
1#
#57500000
0#
#58000000
b0 @
1#
#58500000
0#
#59000000
b110 @
b11 4
1#
#59500000
0#
#60000000
b1 @
b110 4
1#
#60500000
0#
#61000000
b110 @
b1 4
1#
#61500000
0#
#62000000
b110 4
1#
#62500000
0#
#63000000
b101 4
1#
#63500000
0#
#64000000
b1 @
b1 4
1#
#64500000
0#
#65000000
b10 @
b0 4
1#
#65500000
0#
#66000000
b0 @
b11 4
1#
#66500000
0#
#67000000
b110 @
b0 4
1#
#67500000
0#
#68000000
b111 @
b101 4
1#
#68500000
0#
#69000000
b0 @
b10 4
1#
#69500000
0#
#70000000
b111 4
1#
#70500000
0#
#71000000
b10 4
1#
#71500000
0#
#72000000
b1 4
1#
#72500000
0#
#73000000
b1 @
b0 4
1#
#73500000
0#
#74000000
b0 @
1#
#74500000
0#
#75000000
b111 @
b11 4
1#
#75500000
0#
#76000000
b0 @
b1 4
1#
#76500000
0#
#77000000
b110 4
1#
#77500000
0#
#78000000
b10 4
1#
#78500000
0#
#79000000
b1 @
b110 4
1#
#79500000
0#
#80000000
b11 4
1#
#80500000
0#
#81000000
b0 4
1#
#81500000
0#
#82000000
b0 @
1#
#82500000
0#
#83000000
b111 4
1#
#83500000
0#
#84000000
b10 @
b0 4
1#
#84500000
0#
#85000000
b1 @
b101 4
1#
#85500000
0#
#86000000
b0 @
b0 4
1#
#86500000
0#
#87000000
b111 @
b110 4
1#
#87500000
0#
#88000000
b0 @
b10 4
1#
#88500000
0#
#89000000
b10 @
b111 4
1#
#89500000
0#
#90000000
b0 @
b10 4
1#
#90500000
0#
#91000000
b110 @
b1 4
1#
#91500000
0#
#92000000
b10 @
b101 4
1#
#92500000
0#
#93000000
b0 @
b10 4
1#
#93500000
0#
#94000000
b110 @
1#
#94500000
0#
#95000000
b10 @
b1 4
1#
#95500000
0#
#96000000
b0 @
b10 4
1#
#96500000
0#
#97000000
b110 @
1#
#97500000
0#
#98000000
b10 @
b111 4
1#
#98500000
0#
#99000000
b111 @
b110 4
1#
#99500000
0#
#100000000
b110 @
b11 4
1#
#100500000
0#
#101000000
b10 4
1#
#101500000
0#
#102000000
b0 @
b1 4
1#
#102500000
0#
#103000000
b1 @
b101 4
1#
#103500000
0#
#104000000
b111 @
1#
#104500000
0#
#105000000
b110 @
b11 4
1#
#105500000
0#
#106000000
b0 4
1#
#106500000
0#
#107000000
b0 @
b10 4
1#
#107500000
0#
#108000000
b111 @
b1 4
1#
#108500000
0#
#109000000
b10 4
1#
#109500000
0#
#110000000
b0 @
b111 4
1#
#110500000
0#
#111000000
b110 @
b10 4
1#
#111500000
0#
#112000000
1#
#112500000
0#
#113000000
b0 @
b101 4
1#
#113500000
0#
#114000000
b10 4
1#
#114500000
0#
#115000000
b111 @
b11 4
1#
#115500000
0#
#116000000
b0 @
b10 4
1#
#116500000
0#
#117000000
b1 @
b0 4
1#
#117500000
0#
#118000000
b110 @
b10 4
1#
#118500000
0#
#119000000
b11 4
1#
#119500000
0#
#120000000
b111 @
b10 4
1#
#120500000
0#
#121000000
1#
#121500000
0#
#122000000
b110 @
b0 4
1#
#122500000
0#
#123000000
b10 @
b10 4
1#
#123500000
0#
#124000000
b0 @
b101 4
1#
#124500000
0#
#125000000
b111 4
1#
#125500000
0#
#126000000
b1 @
1#
#126500000
0#
#127000000
b111 @
b10 4
1#
#127500000
0#
#128000000
b1 @
b111 4
1#
#128500000
0#
#129000000
b110 @
b0 4
1#
#129500000
0#
#130000000
b10 @
b11 4
1#
#130500000
0#
#131000000
b110 @
b0 4
1#
#131500000
0#
#132000000
b0 @
b11 4
1#
#132500000
0#
#133000000
b10 @
b110 4
1#
#133500000
0#
#134000000
b1 @
b0 4
1#
#134500000
0#
#135000000
b0 @
b1 4
1#
#135500000
0#
#136000000
b111 @
b101 4
1#
#136500000
0#
#137000000
b10 @
b0 4
1#
#137500000
0#
#138000000
b110 @
b110 4
1#
#138500000
0#
#139000000
b0 @
1#
#139500000
0#
#140000000
b11 4
1#
#140500000
0#
#141000000
b10 4
1#
#141500000
0#
#142000000
b110 @
b101 4
1#
#142500000
0#
#143000000
b0 @
1#
#143500000
0#
#144000000
b1 @
b1 4
1#
#144500000
0#
#145000000
b11 4
1#
#145500000
0#
#146000000
b0 @
b111 4
1#
#146500000
0#
#147000000
b111 @
b0 4
1#
#147500000
0#
#148000000
1#
#148500000
0#
#149000000
b110 @
b110 4
1#
#149500000
0#
#150000000
b0 @
b1 4
1#
#150500000
0#
#151000000
b1 @
b11 4
1#
#151500000
0#
#152000000
b110 @
b1 4
1#
#152500000
0#
#153000000
b111 @
b0 4
1#
#153500000
0#
#154000000
b110 @
b111 4
1#
#154500000
0#
#155000000
b0 @
b101 4
1#
#155500000
0#
#156000000
b1 4
1#
#156500000
0#
#157000000
b101 4
1#
#157500000
0#
#158000000
b10 4
1#
#158500000
0#
#159000000
b110 @
b11 4
1#
#159500000
0#
#160000000
b111 @
b110 4
1#
#160500000
0#
#161000000
b0 4
1#
#161500000
0#
#162000000
b10 @
b10 4
1#
#162500000
0#
#163000000
b0 4
1#
#163500000
0#
#164000000
1#
#164500000
0#
#165000000
b101 4
1#
#165500000
0#
#166000000
b0 @
b0 4
1#
#166500000
0#
#167000000
b1 @
1#
#167500000
0#
#168000000
b10 4
1#
#168500000
0#
#169000000
b111 @
b1 4
1#
#169500000
0#
#170000000
b110 @
b11 4
1#
#170500000
0#
#171000000
b111 @
b1 4
1#
#171500000
0#
#172000000
b10 @
1#
#172500000
0#
#173000000
b0 @
b101 4
1#
#173500000
0#
#174000000
b1 @
b11 4
1#
#174500000
0#
#175000000
b0 @
b0 4
1#
#175500000
0#
#176000000
b1 @
b111 4
1#
#176500000
0#
#177000000
b111 @
1#
#177500000
0#
#178000000
b0 @
b0 4
1#
#178500000
0#
#179000000
1#
#179500000
0#
#180000000
b110 @
b10 4
1#
#180500000
0#
#181000000
b0 @
b1 4
1#
#181500000
0#
#182000000
b111 @
b11 4
1#
#182500000
0#
#183000000
b0 @
b110 4
1#
#183500000
0#
#184000000
b111 4
1#
#184500000
0#
#185000000
b1 @
1#
#185500000
0#
#186000000
b10 @
b1 4
1#
#186500000
0#
#187000000
b110 @
b0 4
1#
#187500000
0#
#188000000
1#
#188500000
0#
#189000000
b1 @
b10 4
1#
#189500000
0#
#190000000
b110 @
b1 4
1#
#190500000
0#
#191000000
b10 @
b0 4
1#
#191500000
0#
#192000000
1#
#192500000
0#
#193000000
b1 @
b11 4
1#
#193500000
0#
#194000000
b110 @
b0 4
1#
#194500000
0#
#195000000
1#
#195500000
0#
#196000000
b10 4
1#
#196500000
0#
#197000000
b110 4
1#
#197500000
0#
#198000000
b10 4
1#
#198500000
0#
#199000000
b101 4
1#
#199500000
0#
#200000000
b0 @
1#
#200500000
0#
#201000000
b1 @
b0 4
1#
#201500000
0#
#202000000
b111 @
b10 4
1#
#202500000
0#
#203000000
b1 @
b0 4
1#
#203500000
0#
#204000000
1#
#204500000
0#
#205000000
b0 @
b11 4
1#
#205500000
0#
#206000000
b1 @
b1 4
1#
#206500000
0#
#207000000
b111 4
1#
#207500000
0#
#208000000
b10 @
b0 4
1#
#208500000
0#
#209000000
b0 @
1#
#209500000
0#
#210000000
b110 @
b101 4
1#
#210500000
0#
#211000000
b10 @
b0 4
1#
#211500000
0#
#212000000
b1 4
1#
#212500000
0#
#213000000
b0 @
b10 4
1#
#213500000
0#
#214000000
b101 4
1#
#214500000
0#
#215000000
b1 @
b0 4
1#
#215500000
0#
#216000000
b111 @
b11 4
1#
#216500000
0#
#217000000
b0 4
1#
#217500000
0#
#218000000
b0 @
b10 4
1#
#218500000
0#
#219000000
b10 @
b111 4
1#
#219500000
0#
#220000000
b111 @
b110 4
1#
#220500000
0#
#221000000
b1 4
1#
#221500000
0#
#222000000
b10 @
b110 4
1#
#222500000
0#
#223000000
b0 @
b11 4
1#
#223500000
0#
#224000000
1#
#224500000
0#
#225000000
b110 @
b111 4
1#
#225500000
0#
#226000000
b10 @
b0 4
1#
#226500000
0#
#227000000
b1 4
1#
#227500000
0#
#228000000
b111 @
b0 4
1#
#228500000
0#
#229000000
b1 @
b101 4
1#
#229500000
0#
#230000000
b0 @
b10 4
1#
#230500000
0#
#231000000
b110 @
b11 4
1#
#231500000
0#
#232000000
b0 @
b0 4
1#
#232500000
0#
#233000000
b110 4
1#
#233500000
0#
#234000000
b11 4
1#
#234500000
0#
#235000000
b1 @
b0 4
1#
#235500000
0#
#236000000
b10 @
b10 4
1#
#236500000
0#
#237000000
b11 4
1#
#237500000
0#
#238000000
b111 @
1#
#238500000
0#
#239000000
b0 @
b10 4
1#
#239500000
0#
#240000000
b0 4
1#
#240500000
0#
#241000000
b10 @
b110 4
1#
#241500000
0#
#242000000
b0 @
b101 4
1#
#242500000
0#
#243000000
b110 @
b110 4
1#
#243500000
0#
#244000000
b0 @
b1 4
1#
#244500000
0#
#245000000
b10 @
b110 4
1#
#245500000
0#
#246000000
b0 @
b101 4
1#
#246500000
0#
#247000000
b10 @
b0 4
1#
#247500000
0#
#248000000
b111 @
b101 4
1#
#248500000
0#
#249000000
b10 @
b10 4
1#
#249500000
0#
#250000000
b1 @
b1 4
1#
#250500000
0#
#251000000
b110 @
b0 4
1#
#251500000
0#
#252000000
b0 @
b11 4
1#
#252500000
0#
#253000000
b101 4
1#
#253500000
0#
#254000000
b10 @
b110 4
1#
#254500000
0#
#255000000
b101 4
1#
#255500000
0#
#256000000
b111 @
b111 4
1#
#256500000
0#
#257000000
b10 @
b10 4
1#
#257500000
0#
#258000000
b11 4
1#
#258500000
0#
#259000000
b1 @
b1 4
1#
#259500000
0#
#260000000
b111 @
b111 4
1#
#260500000
0#
#261000000
b0 @
b110 4
1#
#261500000
0#
#262000000
b110 @
b10 4
1#
#262500000
0#
#263000000
b0 @
1#
#263500000
0#
#264000000
b10 @
b1 4
1#
#264500000
0#
#265000000
b111 @
1#
#265500000
0#
#266000000
b1 @
b101 4
1#
#266500000
0#
#267000000
b0 @
b111 4
1#
#267500000
0#
#268000000
b111 @
b0 4
1#
#268500000
0#
#269000000
b1 @
b110 4
1#
#269500000
0#
#270000000
b0 @
1#
#270500000
0#
#271000000
b111 @
b0 4
1#
#271500000
0#
#272000000
b110 @
b101 4
1#
#272500000
0#
#273000000
b111 @
b10 4
1#
#273500000
0#
#274000000
b0 @
b11 4
1#
#274500000
0#
#275000000
b111 @
b0 4
1#
#275500000
0#
#276000000
b0 @
b110 4
1#
#276500000
0#
#277000000
b0 4
1#
#277500000
0#
#278000000
b111 @
1#
#278500000
0#
#279000000
b0 @
b1 4
1#
#279500000
0#
#280000000
b110 @
b0 4
1#
#280500000
0#
#281000000
1#
#281500000
0#
#282000000
b111 @
b10 4
1#
#282500000
0#
#283000000
b10 @
b1 4
1#
#283500000
0#
#284000000
b1 @
b10 4
1#
#284500000
0#
#285000000
b0 @
b0 4
1#
#285500000
0#
#286000000
b10 @
b111 4
1#
#286500000
0#
#287000000
b1 @
b0 4
1#
#287500000
0#
#288000000
b10 @
1#
#288500000
0#
#289000000
1#
#289500000
0#
#290000000
b0 @
b101 4
1#
#290500000
0#
#291000000
b111 @
b1 4
1#
#291500000
0#
#292000000
b0 @
b0 4
1#
#292500000
0#
#293000000
b1 @
1#
#293500000
0#
#294000000
b0 @
b101 4
1#
#294500000
0#
#295000000
b10 @
1#
#295500000
0#
#296000000
b110 @
1#
#296500000
0#
#297000000
b10 @
b110 4
1#
#297500000
0#
#298000000
b110 @
b0 4
1#
#298500000
0#
#299000000
b0 @
b110 4
1#
#299500000
0#
#300000000
b111 4
1#
#300500000
0#
#301000000
b10 @
b101 4
1#
#301500000
0#
#302000000
b111 @
b1 4
1#
#302500000
0#
#303000000
b0 @
b101 4
1#
#303500000
0#
#304000000
b110 @
b0 4
1#
#304500000
0#
#305000000
b1 @
1#
#305500000
0#
#306000000
b10 @
1#
#306500000
0#
#307000000
b0 @
b11 4
1#
#307500000
0#
#308000000
b10 @
1#
#308500000
0#
#309000000
b1 @
b101 4
1#
#309500000
0#
#310000000
b11 4
1#
#310500000
0#
#311000000
b0 @
b0 4
1#
#311500000
0#
#312000000
b10 @
b1 4
1#
#312500000
0#
#313000000
b0 @
b110 4
1#
#313500000
0#
#314000000
b1 @
b0 4
1#
#314500000
0#
#315000000
1#
#315500000
0#
#316000000
b10 @
b110 4
1#
#316500000
0#
#317000000
b101 4
1#
#317500000
0#
#318000000
b1 @
b10 4
1#
#318500000
0#
#319000000
b0 @
1#
#319500000
0#
#320000000
b1 @
b101 4
1#
#320500000
0#
#321000000
b10 @
b11 4
1#
#321500000
0#
#322000000
b10 4
1#
#322500000
0#
#323000000
b1 @
b11 4
1#
#323500000
0#
#324000000
b0 @
b101 4
1#
#324500000
0#
#325000000
b10 @
1#
#325500000
0#
#326000000
b0 @
b11 4
1#
#326500000
0#
#327000000
b0 4
1#
#327500000
0#
#328000000
b111 @
b10 4
1#
#328500000
0#
#329000000
b1 @
b11 4
1#
#329500000
0#
#330000000
b111 @
b10 4
1#
#330500000
0#
#331000000
b0 @
b0 4
1#
#331500000
0#
#332000000
b1 @
b110 4
1#
#332500000
0#
#333000000
b0 @
1#
#333500000
0#
#334000000
b10 @
b101 4
1#
#334500000
0#
#335000000
b110 @
b0 4
1#
#335500000
0#
#336000000
b111 @
b11 4
1#
#336500000
0#
#337000000
b1 @
1#
#337500000
0#
#338000000
b110 @
b101 4
1#
#338500000
0#
#339000000
b111 @
b111 4
1#
#339500000
0#
#340000000
1#
#340500000
0#
#341000000
b0 @
b110 4
1#
#341500000
0#
#342000000
b110 @
b1 4
1#
#342500000
0#
#343000000
b111 @
b110 4
1#
#343500000
0#
#344000000
b10 @
b1 4
1#
#344500000
0#
#345000000
b1 @
b0 4
1#
#345500000
0#
#346000000
b110 @
1#
#346500000
0#
#347000000
b10 @
b101 4
1#
#347500000
0#
#348000000
b0 @
b111 4
1#
#348500000
0#
#349000000
b111 @
b101 4
1#
#349500000
0#
#350000000
b0 @
b0 4
1#
#350500000
0#
#351000000
1#
#351500000
0#
#352000000
b111 @
b10 4
1#
#352500000
0#
#353000000
b110 @
b101 4
1#
#353500000
0#
#354000000
b1 @
b10 4
1#
#354500000
0#
#355000000
b0 @
b11 4
1#
#355500000
0#
#356000000
1#
#356500000
0#
#357000000
b10 @
b0 4
1#
#357500000
0#
#358000000
b110 @
b110 4
1#
#358500000
0#
#359000000
b111 4
1#
#359500000
0#
#360000000
b0 @
b0 4
1#
#360500000
0#
#361000000
b1 4
1#
#361500000
0#
#362000000
b110 @
1#
#362500000
0#
#363000000
b101 4
1#
#363500000
0#
#364000000
b1 @
b110 4
1#
#364500000
0#
#365000000
b11 4
1#
#365500000
0#
#366000000
b110 @
1#
#366500000
0#
#367000000
b0 @
b0 4
1#
#367500000
0#
#368000000
b10 @
1#
#368500000
0#
#369000000
b0 @
b11 4
1#
#369500000
0#
#370000000
b10 @
b101 4
1#
#370500000
0#
#371000000
b1 @
b0 4
1#
#371500000
0#
#372000000
b0 @
b111 4
1#
#372500000
0#
#373000000
b110 @
b1 4
1#
#373500000
0#
#374000000
b0 @
b111 4
1#
#374500000
0#
#375000000
b110 4
1#
#375500000
0#
#376000000
b1 4
1#
#376500000
0#
#377000000
b0 4
1#
#377500000
0#
#378000000
b111 @
1#
#378500000
0#
#379000000
b0 @
b11 4
1#
#379500000
0#
#380000000
b101 4
1#
#380500000
0#
#381000000
b1 @
b0 4
1#
#381500000
0#
#382000000
b10 @
b111 4
1#
#382500000
0#
#383000000
b11 4
1#
#383500000
0#
#384000000
b0 @
b10 4
1#
#384500000
0#
#385000000
b110 @
b111 4
1#
#385500000
0#
#386000000
b10 4
1#
#386500000
0#
#387000000
b10 @
b0 4
1#
#387500000
0#
#388000000
b0 @
1#
#388500000
0#
#389000000
b1 4
1#
