clock.v
/* clock */
`timescale 1ms/1ms
module clock(output clk);
    reg theClock = 1;
    reg [15:0] counter = 0;

    assign clk = theClock;
    
    always begin
        #500;
        theClock = !theClock;
        counter = counter + 1;
        if(counter > 1000) begin
        	//$finish;
        end

    end
endmodule

engine.v
`timescale 1ms/1ms    

/*

ID Legend:
- 0: ?

*/

`define UNKNOWN 0
`define CURRENT 1
`define ENTRANCE 2
`define EXIT 3
`define BLANK 4
`define WALL 5

module main();
	initial begin

		//$dumpfile("cpu.vcd");
		$readmemh("input.data",input_data);
		//$dumpvars(1,main);
		for(i = 0; i < 10; i = i + 1) begin
			for(j = 0; j < 10; j = j + 1) begin
				case(i*10 + j)
					50: begin
						map[i*10 + j] = `ENTRANCE;
					end
					59: begin
						map[i*10 + j] = `EXIT;
					end
					default: begin
						map[i*10 + j] = 4;
					end
				endcase
				bitmap[i*10 + j] = 0;
			end
		end
		//current_pos = 50;
	end

	integer f, number;
	reg[15:0]i; //multi-purpose indices
	reg[15:0]j;
	reg[15:0]eip = 0; //command pointer
	wire clk;
	clock c0(clk);

	reg [15:0]input_data[0:99]; //Array of all command data
	reg [15:0]map[99:0]; //pseudo 10x10 2D array of 16 bit values
	reg bitmap[99:0]; //Literally a bitmap haha
	reg display_queued;

	reg [15:0]current_pos = 50;

	wire[15:0] test1 = map[0];
	wire[15:0] test_data = input_data[0];

	wire[15:0] current_command = input_data[eip];

	wire new_command = !(^input_data[eip] === 1'bx);

	wire left_clear = (current_pos - 1 > 0 && (current_pos - 1) % 10 < current_pos % 10);
	wire left_2_clear = (current_pos - 2 > 0 && (current_pos - 2) % 10 < current_pos % 10);
	wire right_clear = (current_pos + 1 < 100 && (current_pos + 1) % 10 > current_pos % 10);
	wire right_2_clear = (current_pos + 2 < 100 && (current_pos + 2) % 10 > current_pos % 10);
	wire top_clear = (current_pos - 10 > 0);
	wire top_2_clear = (current_pos - 20 > 0);
	wire bottom_clear = (current_pos + 10 < 100);
	wire bottom_2_clear = (current_pos + 20 < 100);

	always @(posedge clk) begin
		

		if(top_clear) begin
			bitmap[current_pos - 10] = 1;
			if(left_clear)
				bitmap[current_pos - 10 - 1] = 1;
			if(right_clear)
				bitmap[current_pos - 10 + 1] = 1;
		end
		if(top_2_clear)
			bitmap[current_pos - 20] = 1;			
		if(bottom_clear) begin
			bitmap[current_pos + 10] = 1;
			if(left_clear)
				bitmap[current_pos + 10 - 1] = 1;
			if(right_clear)
				bitmap[current_pos + 10 + 1] = 1;			
		end
		if(bottom_2_clear)
			bitmap[current_pos + 20] = 1;
		if(right_clear)
			bitmap[current_pos + 1] = 1;
		if(right_2_clear)
			bitmap[current_pos + 2] = 1;			
		if(left_clear)
			bitmap[current_pos - 1] = 1;
		if(left_2_clear)
			bitmap[current_pos - 2] = 1;

		if(new_command) begin //prints out current information
			
			display_queued <= 1;

			case(input_data[eip])
				1: begin
					current_pos <= current_pos + 1;
				end
				2: begin //left
					current_pos <= current_pos - 1;
				end
				3: begin //up
					current_pos <= current_pos - 10;
				end
				4: begin //down
					current_pos <= current_pos + 10;
				end		
				5: begin //exit
					$finish;
				end											
			endcase
			eip <= eip + 1;
		end
		else begin
			//for(i = 0; i < 30; i = i + 1)
				//$display("");
			$readmemh("input.data",input_data);
		end

		if(display_queued) begin
			if(!new_command)
				display_queued <= 0; 
			f = $fopen("output.data");
			$fdisplay(f, "= = = = = = = = = = = = = = = = = = = = =");
			$fdisplay(f, "");
			$fdisplay(f, "");
			$fdisplay(f, "          MAP          ");
			$fdisplay(f, "- - - - - - - - - - - - - -");
			$fdisplay(f, "");
			for(i = 0; i < 10; i = i + 1) begin
				$fwrite(f, "");
				for(j = 0; j < 10; j = j + 1) begin
					if(current_pos == i*10 + j) begin
						$fwrite(f, "! " );
					end
					else if(bitmap[i*10 + j] == 0) begin
						$fwrite(f, "? " );
					end
					else begin
						case(map[i*10 + j])
							`CURRENT: begin
								$fwrite(f, "! ");
							end
							`ENTRANCE: begin
								$fwrite(f, "< ");
							end
							`EXIT: begin
								$fwrite(f, "> ");
							end		
							`BLANK: begin
								$fwrite(f, "  ");
							end
							`WALL: begin
								$fwrite(f, "X ");
							end												

						endcase							
					end
				end
				$fdisplay(f, "");
			end	

			$fdisplay(f, "");
			$fdisplay(f, "");
			$fdisplay(f, "= = = = = = = = = = = = = = = = = = = = =");
			$fclose(f);
		end
	end


endmodule

dump.vcd
$date
	Tue Dec  1 16:25:34 2015
$end
$version
	Icarus Verilog
$end
$timescale
	1ms
$end
$scope module main $end
$var wire 1 ! bottom_2_clear $end
$var wire 1 " bottom_clear $end
$var wire 1 # clk $end
$var wire 16 $ current_command [15:0] $end
$var wire 1 % left_2_clear $end
$var wire 1 & left_clear $end
$var wire 1 ' new_command $end
$var wire 1 ( right_2_clear $end
$var wire 1 ) right_clear $end
$var wire 16 * test1 [15:0] $end
$var wire 16 + test_data [15:0] $end
$var wire 1 , top_2_clear $end
$var wire 1 - top_clear $end
$var reg 16 . current_pos [15:0] $end
$var reg 1 / display_queued $end
$var reg 16 0 eip [15:0] $end
$var integer 32 1 f [31:0] $end
$var reg 16 2 i [15:0] $end
$var reg 16 3 j [15:0] $end
$upscope $end
$enddefinitions $end
#0
$dumpvars
b1010 3
b1010 2
bx 1
b0 0
x/
b110010 .
1-
1,
b0 +
b100 *
1)
1(
1'
0&
0%
b0 $
1#
1"
1!
$end
#500
0#
#1000
b1 0
b1 $
1/
1#
#1500
0#
#2000
1&
b10 0
b110011 .
b1010 3
b1010 2
b10 1
1#
#2500
0#
#3000
1%
b11 0
b110100 .
b1010 3
b1010 2
1#
#3500
0#
#4000
b100 0
b110101 .
b1010 3
b1010 2
1#
#4500
0#
#5000
b101 0
b110110 .
b1010 3
b1010 2
1#
#5500
0#
#6000
b110 0
b110111 .
b1010 3
b1010 2
1#
#6500
0#
#7000
b111 0
b111000 .
b1010 3
b1010 2
1#
#7500
0#
#8000
b1000 0
bx $
0'
b111001 .
b1010 3
b1010 2
1#
#8500
0#
#9000
0/
b1010 3
b1010 2
1#
